main.py
tuskr_client.py
tuskr_mcp_server-0.1.1.dist-info/licenses/LICENSE
tuskr_mcp_server-0.1.1.dist-info/METADATA
tuskr_mcp_server-0.1.1.dist-info/WHEEL
tuskr_mcp_server-0.1.1.dist-info/entry_points.txt
tuskr_mcp_server-0.1.1.dist-info/top_level.txt
tuskr_mcp_server-0.1.1.dist-info/RECORD
