Metadata-Version: 2.4
Name: tuskr-mcp-server
Version: 0.1.1
Summary: Add your description here
Author-email: Ruslan Galinskii <galinskyifmo@gmail.com>
License: MIT
Project-URL: Homepage, https://github.com/BoomBidiBuyBuy/tuskr-mcp-server
Project-URL: Repository, https://github.com/BoomBidiBuyBuy/tuskr-mcp-server.git
Project-URL: Bug Tracker, https://github.com/BoomBidiBuyBuy/tuskr-mcp-server/issues
Keywords: mcp,tuskr,model-context-protocol
Requires-Python: >=3.12
License-File: LICENSE
Requires-Dist: click>=8.2.1
Requires-Dist: fastmcp>=2.10.4
Requires-Dist: requests>=2.32.4
Dynamic: license-file
